vba_edit/__init__.py
vba_edit/access_vba.py
vba_edit/cli_common.py
vba_edit/console.py
vba_edit/excel_vba.py
vba_edit/exceptions.py
vba_edit/help_formatter.py
vba_edit/office_vba.py
vba_edit/path_utils.py
vba_edit/powerpoint_vba.py
vba_edit/utils.py
vba_edit/word_vba.py
vba_edit-0.4.1.dist-info/licenses/AUTHORS.md
vba_edit-0.4.1.dist-info/licenses/LICENSE
vba_edit-0.4.1.dist-info/licenses/SECURITY.md
vba_edit-0.4.1.dist-info/licenses/LICENSES/LICENSE-xlwings.txt
vba_edit-0.4.1.dist-info/METADATA
vba_edit-0.4.1.dist-info/WHEEL
vba_edit-0.4.1.dist-info/entry_points.txt
vba_edit-0.4.1.dist-info/top_level.txt
vba_edit-0.4.1.dist-info/RECORD
