Metadata-Version: 2.4
Name: vba_edit
Version: 0.4.1
Summary: Enable seamless MS Office VBA code editing in preferred editor or IDE (facilitating the use of coding assistants and version control workflows)
Author-email: Markus Killer <m.killer@langui.ch>
License-Expression: BSD-3-Clause
Project-URL: Homepage, https://langui.ch/current-projects/vba-edit/
Project-URL: Documentation, https://github.com/markuskiller/vba-edit/blob/main/README.md
Project-URL: Source, https://github.com/markuskiller/vba-edit
Project-URL: Changelog, https://github.com/markuskiller/vba-edit/blob/main/CHANGELOG.md
Keywords: vba,excel,word,office,automation,macro,PyPI
Classifier: Development Status :: 3 - Alpha
Classifier: Intended Audience :: Developers
Classifier: Programming Language :: Python :: 3
Classifier: Programming Language :: Python :: 3.9
Classifier: Programming Language :: Python :: 3.10
Classifier: Programming Language :: Python :: 3.11
Classifier: Programming Language :: Python :: 3.12
Classifier: Programming Language :: Python :: 3.13
Classifier: Programming Language :: Python :: 3.14
Classifier: Programming Language :: Python :: Implementation :: CPython
Classifier: Operating System :: Microsoft :: Windows
Classifier: Topic :: Office/Business :: Office Suites
Requires-Python: >=3.9
License-File: LICENSE
License-File: LICENSES/LICENSE-xlwings.txt
License-File: AUTHORS.md
License-File: SECURITY.md
Requires-Dist: chardet
Requires-Dist: pywin32>=224; platform_system == "Windows"
Requires-Dist: watchfiles>=1.1.1
Requires-Dist: tomli>=2.0.0; python_version < "3.11"
Requires-Dist: rich>=13.0.0
Provides-Extra: dev
Requires-Dist: black; extra == "dev"
Requires-Dist: ruff; extra == "dev"
Requires-Dist: pytest; extra == "dev"
Requires-Dist: pytest-cov>=4.0.0; extra == "dev"
Requires-Dist: pytest-timeout>=2.0.0; extra == "dev"
Requires-Dist: twine; extra == "dev"
Requires-Dist: wheel; extra == "dev"
Requires-Dist: pyinstaller; extra == "dev"
Provides-Extra: all
Requires-Dist: xlwings>=0.28.0; extra == "all"
Dynamic: license-file
